Workbook

Sheet Summary
B2: DBM Portal — Build Cost (One-time)
B3: Engineering effort × blended rate, plus design / QA / PM / contingency, plus non-labor hard costs.
B4: Phase 1 is already shipped (greyed Done on Hours sheet). 'Remaining build' is what's left to ship Phases 2-7.
B6: Scenario | C6: $/hr | D6: Eng cost | E6: +Design/QA/PM | F6: +Contingency | G6: Total build
B7: Solo / founder-built (you + AI) | C7: =Rates!C6 -> 50 | D7: =Hours!D37*Rates!C6 -> 82400 | E7: =D7*(1+Rates!C14+Rates!C15+Rates!C16) -> 119480 | F7: =E7*(1+Rates!C17) -> 137402 | G7: =F7+Rates!C32 -> 143106
B8: Offshore agency | C8: =Rates!C7 -> 40 | D8: =Hours!D37*Rates!C7 -> 65920 | E8: =D8*(1+Rates!C14+Rates!C15+Rates!C16) -> 95584 | F8: =E8*(1+Rates!C17) -> 109921.6 | G8: =F8+Rates!C32 -> 115625.6
B9: US contractor / boutique | C9: =Rates!C8 -> 110 | D9: =Hours!D37*Rates!C8 -> 181280 | E9: =D9*(1+Rates!C14+Rates!C15+Rates!C16) -> 262856 | F9: =E9*(1+Rates!C17) -> 302284.4 | G9: =F9+Rates!C32 -> 307988.4
B10: US FTE blended | C10: =Rates!C9 -> 140 | D10: =Hours!D37*Rates!C9 -> 230720 | E10: =D10*(1+Rates!C14+Rates!C15+Rates!C16) -> 334544 | F10: =E10*(1+Rates!C17) -> 384725.6 | G10: =F10+Rates!C32 -> 390429.6
B13: Build cost by phase (at solo/founder rate)
B14: Phase | C14: Hours | D14: Eng cost | E14: +D/Q/PM | F14: +Contingency | G14: Status
B15: P1 — Find (search, directory) | C15: =SUMIFS(Hours!D6:D35,Hours!B6:B35,"P1")+SUMIFS(Hours!E6:E35,Hours!B6:B35,"P1")+SUMIFS(Hours!F6:F35,Hours!B6:B35,"P1") -> 272 | D15: =C15*Rates!C6 -> 13600 | E15: =D15*(1+Rates!C14+Rates!C15+Rates!C16) -> 19720 | F15: =E15*(1+Rates!C17) -> 22678 | G15: Done
B16: P2 — Get bids | C16: =SUMIFS(Hours!D6:D35,Hours!B6:B35,"P2")+SUMIFS(Hours!E6:E35,Hours!B6:B35,"P2")+SUMIFS(Hours!F6:F35,Hours!B6:B35,"P2") -> 284 | D16: =C16*Rates!C6 -> 14200 | E16: =D16*(1+Rates!C14+Rates!C15+Rates!C16) -> 20590 | F16: =E16*(1+Rates!C17) -> 23678.5 | G16: Remaining
B17: P3 — Compare bids | C17: =SUMIFS(Hours!D6:D35,Hours!B6:B35,"P3")+SUMIFS(Hours!E6:E35,Hours!B6:B35,"P3")+SUMIFS(Hours!F6:F35,Hours!B6:B35,"P3") -> 228 | D17: =C17*Rates!C6 -> 11400 | E17: =D17*(1+Rates!C14+Rates!C15+Rates!C16) -> 16530 | F17: =E17*(1+Rates!C17) -> 19009.5 | G17: Remaining
B18: P4 — Sign contract | C18: =SUMIFS(Hours!D6:D35,Hours!B6:B35,"P4")+SUMIFS(Hours!E6:E35,Hours!B6:B35,"P4")+SUMIFS(Hours!F6:F35,Hours!B6:B35,"P4") -> 152 | D18: =C18*Rates!C6 -> 7600 | E18: =D18*(1+Rates!C14+Rates!C15+Rates!C16) -> 11020 | F18: =E18*(1+Rates!C17) -> 12673 | G18: Remaining
B19: P5 — Execute contract | C19: =SUMIFS(Hours!D6:D35,Hours!B6:B35,"P5")+SUMIFS(Hours!E6:E35,Hours!B6:B35,"P5")+SUMIFS(Hours!F6:F35,Hours!B6:B35,"P5") -> 448 | D19: =C19*Rates!C6 -> 22400 | E19: =D19*(1+Rates!C14+Rates!C15+Rates!C16) -> 32480 | F19: =E19*(1+Rates!C17) -> 37352 | G19: Remaining
B20: P6 — Close contract | C20: =SUMIFS(Hours!D6:D35,Hours!B6:B35,"P6")+SUMIFS(Hours!E6:E35,Hours!B6:B35,"P6")+SUMIFS(Hours!F6:F35,Hours!B6:B35,"P6") -> 132 | D20: =C20*Rates!C6 -> 6600 | E20: =D20*(1+Rates!C14+Rates!C15+Rates!C16) -> 9570 | F20: =E20*(1+Rates!C17) -> 11005.5 | G20: Remaining
B21: P7 — Reviews | C21: =SUMIFS(Hours!D6:D35,Hours!B6:B35,"P7")+SUMIFS(Hours!E6:E35,Hours!B6:B35,"P7")+SUMIFS(Hours!F6:F35,Hours!B6:B35,"P7") -> 132 | D21: =C21*Rates!C6 -> 6600 | E21: =D21*(1+Rates!C14+Rates!C15+Rates!C16) -> 9570 | F21: =E21*(1+Rates!C17) -> 11005.5 | G21: Remaining
B22: TOTAL (all phases) | C22: =SUM(C15:C21) -> 1648 | D22: =SUM(D15:D21) -> 82400 | E22: =SUM(E15:E21) -> 119480 | F22: =SUM(F15:F21) -> 137402
B23: REMAINING (P2–P7 only) | C23: =SUM(C16:C21) -> 1376 | D23: =SUM(D16:D21) -> 68800 | E23: =SUM(E16:E21) -> 99760 | F23: =SUM(F16:F21) -> 114724
B25: Calendar time (solo, ~30 hrs/week productive)
B26: Remaining hours / 30 hrs per week | C26: =C23/30 -> 45.866667 | D26: weeks | E26: =C26/4.3 -> 10.666667 | F26: months
B29: What's included / excluded
B30: Included | C30: Backend (NestJS+Prisma+Postgres), Frontend (Next.js), Mobile (Expo), 3rd-party integrations (Firebase, Claude, R2, DocuSign, Stripe Connect, Pusher, SendGrid), DevOps on Render, app-store submissions, light security review, ToS/Privacy legal.
B31: Excluded | C31: Ongoing hosting/opex (in separate cost model), AI usage cost (in opex), marketing/CAC, customer support, dedicated SRE, SOC 2 audit, advanced security pen test, multi-region HA, future city permit/building-rules API integration.
B32: Future scope | C32: Per-city integration with municipal APIs for permit/license lookup and building-code rules. Each city ≈ 60–120 hrs + possible API/data fees. Track separately when committed.

Sheet Rates
B2: Blended Engineering Rates ($/hour)
B3: Edit these to flex the whole model. Three scenarios drive the Summary.
B5: Scenario | C5: Blended $/hr | D5: Notes
B6: Solo / founder-built | C6: 50 | D6: You + AI agents (this build). Out-of-pocket = cloud + tools only; time is opportunity cost.
B7: Offshore agency | C7: 40 | D7: India / LATAM senior+mid mix. Full QA + PM included.
B8: US contractor / boutique | C8: 110 | D8: US-based senior contractor blended with mid. No benefits.
B9: US FTE blended | C9: 140 | D9: Loaded cost (salary + benefits + tax + tools) ÷ ~1,800 productive hours.
B12: Multipliers
B13: Item | C13: Value | D13: Notes
B14: Design % of build | C14: 0.15 | D14: UI/UX work as % of engineering hours. Set 0 if design is bundled.
B15: QA % of build | C15: 0.2 | D15: Manual + automated QA hours as % of engineering.
B16: PM / coordination % | C16: 0.1 | D16: PM, standups, vendor coord, docs.
B17: Contingency % | C17: 0.15 | D17: Risk buffer for scope creep, integrations, retries.
B20: One-time hard costs (non-labor)
B21: Item | C21: $ | D21: Notes
B22: Apple Developer Program | C22: 99 | D22: Required to ship iOS / Sign in with Apple. Annual.
B23: Google Play Developer | C23: 25 | D23: One-time.
B24: Domain + email (yr 1) | C24: 100 | D24: Domain, Google Workspace seat, transactional sender.
B25: Design tools (Figma yr 1) | C25: 180 | D25: $15/mo × 12. Skip if solo.
B26: Logo / brand identity | C26: 500 | D26: One-shot Fiverr/Upwork. Skip if DIY.
B27: Legal — ToS / Privacy / DPA | C27: 1500 | D27: Template + lawyer review. Required before public launch.
B28: Security review / pen test (light) | C28: 3000 | D28: Pre-launch external review. Recommended pre-Phase 5.
B29: DocuSign sandbox + setup | C29: 0 | D29: Free for dev. Production billed per envelope (opex).
B30: Stripe Connect onboarding | C30: 0 | D30: Free; fees are passthrough (opex).
B31: App store assets / screenshots | C31: 300 | D31: Per platform. Designer or DIY.
B32: Subtotal — One-time hard costs | C32: =SUM(C22:C31) -> 5704

Sheet Hours
B2: Engineering Hours by Phase
B3: Effort estimate for a senior generalist building with AI assistance. Phase 1 is already shipped (marked Done).
B5: Phase | C5: Module | D5: Backend hrs | E5: Frontend hrs | F5: Mobile hrs | G5: Scope / Notes
B6: P1 | C6: Auth & accounts (Firebase, email/Google) | D6: 24 | E6: 20 | F6: 8 | G6: Sign-up, sign-in, password reset, sessions, role gating. ✅ Shipped.
B7: P1 | C7: Pro directory & search | D7: 40 | E7: 32 | F7: 12 | G7: Profile model, search indexing, filters by trade/zip. ✅ Shipped.
B8: P1 | C8: Pro profile + portfolio uploads | D8: 28 | E8: 24 | F8: 8 | G8: Photos, services, license fields, R2 storage. ✅ Shipped.
B9: P1 | C9: Admin moderation basics | D9: 16 | E9: 12 | F9: 0 | G9: Flag, approve, suspend. ✅ Shipped.
B10: P1 | C10: Mobile shell (Expo) + deep links | D10: 8 | E10: 0 | F10: 40 | G10: Tab nav, auth, profile screens. ✅ Shipped.
B11: P2 | C11: Bid request flow (homeowner) | D11: 32 | E11: 36 | F11: 16 | G11: Project scope form, photo/PDF upload, location.
B12: P2 | C12: Bid form for pros (respond) | D12: 28 | E12: 28 | F12: 12 | G12: Line items, attachments, validity window.
B13: P2 | C13: AI scope scan (Claude + vision) | D13: 40 | E13: 16 | F13: 0 | G13: Parse uploaded plans, extract scope, generate checklist. Anthropic Claude.
B14: P2 | C14: Lead matching + delivery | D14: 24 | E14: 12 | F14: 0 | G14: Match homeowner request to qualified pros; throttle, $25/lead billing hook.
B15: P2 | C15: Notifications (email + push) | D15: 20 | E15: 8 | F15: 12 | G15: SendGrid email + Expo push tokens.
B16: P3 | C16: Bid comparison UI | D16: 16 | E16: 40 | F16: 12 | G16: Side-by-side line-item compare, totals, conditions.
B17: P3 | C17: Negotiation / counter-offer thread | D17: 28 | E17: 24 | F17: 16 | G17: Threaded messages, attachments, status.
... B35: P7 | C35: Trust & safety (search + moderation) | D35: 24 | E35: 16 | F35: 4 | G35: Search ranking guardrails, abuse reporting.
C36: TOTAL Engineering Hours | D36: =SUM(D6:D35) -> 768 | E36: =SUM(E6:E35) -> 596 | F36: =SUM(F6:F35) -> 284
C37: GRAND TOTAL Engineering Hours | D37: =SUM(D36:F36) -> 1648
